otlp_proto-0.10.1.dist-info/METADATA
otlp_proto-0.10.1.dist-info/WHEEL
otlp_proto.libs/libgcc_s-e52197c3.so.1
otlp_proto/__init__.py
otlp_proto/__init__.pyi
otlp_proto/otlp_proto.cpython-39-aarch64-linux-gnu.so
otlp_proto/py.typed
otlp_proto-0.10.1.dist-info/RECORD
