Metadata-Version: 2.4
Name: otlp-proto
Version: 0.10.1
Classifier: Development Status :: 3 - Alpha
Classifier: Intended Audience :: Developers
Classifier: License :: OSI Approved :: MIT License
Classifier: Natural Language :: English
Classifier: Operating System :: OS Independent
Classifier: Programming Language :: Python
Classifier: Programming Language :: Python :: 3
Classifier: Programming Language :: Python :: 3.8
Classifier: Programming Language :: Python :: 3.9
Classifier: Programming Language :: Python :: 3.10
Classifier: Programming Language :: Python :: 3.11
Classifier: Programming Language :: Python :: 3.12
Classifier: Programming Language :: Python :: 3.13
Classifier: Programming Language :: Python :: 3 :: Only
Classifier: Programming Language :: Python :: Implementation :: CPython
Classifier: Programming Language :: Python :: Implementation :: PyPy
Classifier: Programming Language :: Rust
Classifier: Topic :: Software Development :: Libraries
Classifier: Framework :: OpenTelemetry
Classifier: Framework :: OpenTelemetry :: Exporters
Summary: 🐍Lightweight OTEL span to binary converter, written in Rust🦀
License: MIT
Requires-Python: >=3.8
Project-URL: Repository, https://github.com/dimaqq/otlp-proto
Project-URL: Issues, https://github.com/dimaqq/otlp-proto/issues
